codemie_client/__init__.py
codemie_client/client.py
codemie_client/models.py
codemie_client/service/__init__.py
codemie_client/service/assistants.py
codemie_client/service/auth.py
codemie_client-0.1.11.dist-info/LICENSE
codemie_client-0.1.11.dist-info/METADATA
codemie_client-0.1.11.dist-info/WHEEL
codemie_client-0.1.11.dist-info/RECORD
