Metadata-Version: 2.1
Name: codemie-client
Version: 0.1.11
Summary: CodeMie Client
Author: Vadym Vlasenko
Author-email: vadym_vlasenko@epam.com
Requires-Python: >=3.11,<4.0
Classifier: Programming Language :: Python :: 3
Classifier: Programming Language :: Python :: 3.11
Classifier: Programming Language :: Python :: 3.12
Requires-Dist: PyGithub (>=2.2.0,<3.0.0)
Requires-Dist: pydantic (>=1.9.0,<2.0.0)
Requires-Dist: requests (>=2.27.1,<3.0.0)
